{
	"cmake" : 
	{
		"generator" : 
		{
			"multiConfig" : false,
			"name" : "MinGW Makefiles"
		},
		"paths" : 
		{
			"cmake" : "D:/Software/Jetbrains/apps/CLion/ch-0/223.8836.42/bin/cmake/win/x64/bin/cmake.exe",
			"cpack" : "D:/Software/Jetbrains/apps/CLion/ch-0/223.8836.42/bin/cmake/win/x64/bin/cpack.exe",
			"ctest" : "D:/Software/Jetbrains/apps/CLion/ch-0/223.8836.42/bin/cmake/win/x64/bin/ctest.exe",
			"root" : "D:/Software/Jetbrains/apps/CLion/ch-0/223.8836.42/bin/cmake/win/x64/share/cmake-3.24"
		},
		"version" : 
		{
			"isDirty" : false,
			"major" : 3,
			"minor" : 24,
			"patch" : 2,
			"string" : "3.24.2",
			"suffix" : ""
		}
	},
	"objects" : 
	[
		{
			"jsonFile" : "codemodel-v2-2f695591db05ab273eff.json",
			"kind" : "codemodel",
			"version" : 
			{
				"major" : 2,
				"minor" : 4
			}
		},
		{
			"jsonFile" : "cache-v2-d9d609a2ca27c71973a0.json",
			"kind" : "cache",
			"version" : 
			{
				"major" : 2,
				"minor" : 0
			}
		},
		{
			"jsonFile" : "cmakeFiles-v1-867d4c0543359ac46ef4.json",
			"kind" : "cmakeFiles",
			"version" : 
			{
				"major" : 1,
				"minor" : 0
			}
		},
		{
			"jsonFile" : "toolchains-v1-68ad53ffb5717f1da9ff.json",
			"kind" : "toolchains",
			"version" : 
			{
				"major" : 1,
				"minor" : 0
			}
		}
	],
	"reply" : 
	{
		"cache-v2" : 
		{
			"jsonFile" : "cache-v2-d9d609a2ca27c71973a0.json",
			"kind" : "cache",
			"version" : 
			{
				"major" : 2,
				"minor" : 0
			}
		},
		"cmakeFiles-v1" : 
		{
			"jsonFile" : "cmakeFiles-v1-867d4c0543359ac46ef4.json",
			"kind" : "cmakeFiles",
			"version" : 
			{
				"major" : 1,
				"minor" : 0
			}
		},
		"codemodel-v2" : 
		{
			"jsonFile" : "codemodel-v2-2f695591db05ab273eff.json",
			"kind" : "codemodel",
			"version" : 
			{
				"major" : 2,
				"minor" : 4
			}
		},
		"toolchains-v1" : 
		{
			"jsonFile" : "toolchains-v1-68ad53ffb5717f1da9ff.json",
			"kind" : "toolchains",
			"version" : 
			{
				"major" : 1,
				"minor" : 0
			}
		}
	}
}
